hashsoup/__init__.py
hashsoup/hasher.py
hashsoup/md2.py
hashsoup/md4.py
hashsoup/md5.py
hashsoup/utils.py
hashsoup-0.1.0.post1.dist-info/LICENSE
hashsoup-0.1.0.post1.dist-info/METADATA
hashsoup-0.1.0.post1.dist-info/WHEEL
hashsoup-0.1.0.post1.dist-info/top_level.txt
hashsoup-0.1.0.post1.dist-info/RECORD
